timer/timer.sv
module timer(
       input clk,  // clock
       input rst,  // reset
       output reg [63:0] t // 64-bit output register of time
       );

  always_ff @(posedge clk or posedge rst)
    if(rst)
      t <= 0;
    else
      t <= t+1;
endmodule

timer/tb_timer.sv
module tb_timer(
        output logic clk,  // generated clock
        output logic rst,  // generated reset
        output [63:0] t    // test output
        );

  initial begin
    $dumpfile("tb_timer_trace.vcd"); // dump signal changes
    $dumpvars();                     // dump all variables in this module
    clk = 1;                         // value of clk at simulation step 0
    rst = 1;                         // value of rst at simulation step 0
    #20 rst = 0;                     // wait 20 simulation steps and then lower rst
    #100 $finish();                  // wait 100 simulation steps, then call $finish() to stop
  end

  // invert the clock every 5 simulation steps
  always #5 clk = !clk;

  // initatiate the design under test (DUT)
  timer dut(.clk(clk), .rst(rst), .t(t));

  // every negative edge of the clock, output the status
  always @(posedge clk)
    $display("sim_time=%4d      t=%4d", $time, t);
   
endmodule

timer/tb_timer_trace.vcd
$version Generated by VerilatedVcd $end
$timescale 1ps $end
 $scope module $rootio $end
  $var wire 1 # clk $end
  $var wire 1 $ rst $end
  $var wire 64 % t [63:0] $end
 $upscope $end
 $scope module tb_timer $end
  $var wire 1 # clk $end
  $var wire 1 $ rst $end
  $var wire 64 % t [63:0] $end
  $scope module dut $end
   $var wire 1 # clk $end
   $var wire 1 $ rst $end
   $var wire 64 % t [63:0] $end
  $upscope $end
 $upscope $end
$enddefinitions $end


#0
1#
1$
b0000000000000000000000000000000000000000000000000000000000000000 %
#5
0#
#10
1#
#15
0#
#20
1#
0$
b0000000000000000000000000000000000000000000000000000000000000001 %
#25
0#
#30
1#
b0000000000000000000000000000000000000000000000000000000000000010 %
#35
0#
#40
1#
b0000000000000000000000000000000000000000000000000000000000000011 %
#45
0#
#50
1#
b0000000000000000000000000000000000000000000000000000000000000100 %
#55
0#
#60
1#
b0000000000000000000000000000000000000000000000000000000000000101 %
#65
0#
#70
1#
b0000000000000000000000000000000000000000000000000000000000000110 %
#75
0#
#80
1#
b0000000000000000000000000000000000000000000000000000000000000111 %
#85
0#
#90
1#
b0000000000000000000000000000000000000000000000000000000000001000 %
#95
0#
#100
1#
b0000000000000000000000000000000000000000000000000000000000001001 %
#105
0#
#110
1#
b0000000000000000000000000000000000000000000000000000000000001010 %
#115
0#
#120
1#
b0000000000000000000000000000000000000000000000000000000000001011 %
